django_sayit-1.5.dist-info/DESCRIPTION.rst
django_sayit-1.5.dist-info/METADATA
django_sayit-1.5.dist-info/RECORD
django_sayit-1.5.dist-info/WHEEL
django_sayit-1.5.dist-info/metadata.json
django_sayit-1.5.dist-info/pbr.json
django_sayit-1.5.dist-info/top_level.txt
speeches/__init__.py
speeches/admin.py
speeches/api.py
speeches/colour.py
speeches/fields.py
speeches/forms.py
speeches/middleware.py
speeches/mixins.py
speeches/models.py
speeches/search.py
speeches/search_indexes.py
speeches/thumbnail_processors.py
speeches/urls.py
speeches/views.py
speeches/widgets.py
speeches/external/__init__.py
speeches/external/formencode.py
speeches/importers/__init__.py
speeches/importers/import_akomantoso.py
speeches/importers/import_base.py
speeches/importers/import_popolo.py
speeches/locale/de/LC_MESSAGES/django.mo
speeches/locale/de/LC_MESSAGES/django.po
speeches/locale/el/LC_MESSAGES/django.mo
speeches/locale/el/LC_MESSAGES/django.po
speeches/locale/en/LC_MESSAGES/.gitignore
speeches/locale/en/LC_MESSAGES/django.mo
speeches/locale/en/LC_MESSAGES/django.po
speeches/locale/es/LC_MESSAGES/django.mo
speeches/locale/es/LC_MESSAGES/django.po
speeches/locale/he/LC_MESSAGES/django.mo
speeches/locale/he/LC_MESSAGES/django.po
speeches/locale/hu_HU/LC_MESSAGES/django.mo
speeches/locale/hu_HU/LC_MESSAGES/django.po
speeches/locale/my_MM/LC_MESSAGES/django.mo
speeches/locale/my_MM/LC_MESSAGES/django.po
speeches/locale/sk/LC_MESSAGES/django.mo
speeches/locale/sk/LC_MESSAGES/django.po
speeches/locale/zh_TW/LC_MESSAGES/django.mo
speeches/locale/zh_TW/LC_MESSAGES/django.po
speeches/management/__init__.py
speeches/management/import_commands.py
speeches/management/commands/__init__.py
speeches/management/commands/load_akomantoso.py
speeches/management/commands/load_shakespeare.py
speeches/management/commands/sayit_load_speakers.py
speeches/management/commands/sayit_search_make_index_live.py
speeches/management/commands/sayit_search_new_index.py
speeches/migrations/0001_initial.py
speeches/migrations/0002_auto_20151112_2003.py
speeches/migrations/0003_auto_20170323_0932.py
speeches/migrations/__init__.py
speeches/static/speeches/css/speeches.css
