Metadata-Version: 2.0
Name: django-sayit
Version: 1.5
Summary: A data store for speeches and transcripts to make them searchable and pretty.
Home-page: https://github.com/mysociety/sayit
Author: mySociety
Author-email: sayit@mysociety.org
License: UNKNOWN
Platform: UNKNOWN
Classifier: Development Status :: 5 - Production/Stable
Classifier: Environment :: Web Environment
Classifier: Framework :: Django
Classifier: License :: OSI Approved :: GNU Affero General Public License v3
Classifier: Intended Audience :: Developers
Classifier: Programming Language :: Python
Classifier: Programming Language :: Python :: 2
Classifier: Programming Language :: Python :: 3
Classifier: Topic :: Database :: Front-Ends
Classifier: Topic :: Internet :: WWW/HTTP
Requires-Dist: Django (>=1.8.5,<2.0)
Requires-Dist: audioread (>=1.0.1)
Requires-Dist: django-bleach (>=0.2.1)
Requires-Dist: django-haystack (>=2.5,<2.6)
Requires-Dist: django-subdomain-instances (>=2.0)
Requires-Dist: easy-thumbnails (>=2.4.1)
Requires-Dist: elasticsearch (>=0.4)
Requires-Dist: mysociety-Django-Select2 (==4.3.2.1)
Requires-Dist: mysociety-django-popolo (>=0.0.5)
Requires-Dist: mysociety-django-sluggable (>=0.2.7)
Requires-Dist: ndg-httpsclient (>=0.3.2)
Requires-Dist: psycopg2 (>=2.5.1,<2.6)
Requires-Dist: pyOpenSSL (>=0.14)
Requires-Dist: pyasn1 (>=0.1.7)
Requires-Dist: pytz (>=2013d)
Requires-Dist: six (>=1.4.1)
Requires-Dist: unicode-slugify (==0.1.1)
Provides-Extra: develop
Requires-Dist: django-debug-toolbar; extra == 'develop'
Requires-Dist: flake8; extra == 'develop'
Provides-Extra: scraping
Requires-Dist: beautifulsoup4; extra == 'scraping'
Provides-Extra: test
Requires-Dist: Mutagen; extra == 'test'
Requires-Dist: django-nose (==1.4.4); extra == 'test'
Requires-Dist: lxml; extra == 'test'
Requires-Dist: mock; extra == 'test'
Requires-Dist: python-dateutil (<2); extra == 'test'
Requires-Dist: requests-cache; extra == 'test'
Requires-Dist: selenium (>=3); extra == 'test'
